Workbook

Sheet Dados_DF
A1: DADOS PÚBLICOS — Bradespar S.A. — DFs de 31/12/2025 (R$ mil, salvo indicação). Azul = entrada transcrita da fonte.
A3: Chave | B3: Descrição | C3: 2025 | D3: 2024 | E3: Fonte (documento / página impressa)
A4: ativo_total | B4: Total do ativo | C4: 7999560 | D4: 8606884 | E4: Demonstrações Financeiras (DF) p.14 — Balanço
A5: ativo_circ | B5: Ativo circulante | C5: 565128 | D5: 360610 | E5: DF p.14
A6: caixa | B6: Caixa e equivalentes de caixa | C6: 18402 | D6: 287950 | E6: DF p.14; Nota 7 p.26
A7: div_receber | B7: Dividendos e JCP a receber | C7: 546640 | D7: 72276 | E7: DF p.14
A8: investimentos | B8: Investimentos (Vale — equivalência) | C8: 7344756 | D8: 8153681 | E8: DF p.14; Nota 8 p.27
A9: imobilizado | B9: Imobilizado | C9: 899 | D9: 1011 | E9: DF p.14
A10: intangivel | B10: Intangível | C10: 4067 | D10: 2306 | E10: DF p.14; Nota 16b p.34
A11: tributos_rlp | B11: Tributos a compensar (RLP) | C11: 84710 | D11: 89276 | E11: DF p.14; Nota 12a p.31
A12: passivo_circ | B12: Passivo circulante | C12: 347821 | D12: 121412 | E12: DF p.14
A13: passivo_nc | B13: Passivo não circulante | C13: 3968 | D13: 2105 | E13: DF p.14
A14: pl | B14: Patrimônio líquido | C14: 7647771 | D14: 8483367 | E14: DF p.14
A15: div_pagar | B15: Dividendos e JCP a pagar | C15: 316563 | D15: 87936 | E15: DF p.14
... A31: div_receb | B31: Dividendos recebidos de Vale | C31: 349881 | D31: 447354 | E31: Nota 13 I p.32
A32: div_receber_v | B32: Dividendos a receber de Vale | C32: 328708 | E32: Nota 13 I p.32 (2024 não informado)
A33: irrf | B33: Alíquota de IRRF sobre JCP | C33: 0.15 | D33: 0.15 | E33: Nota 10c p.29–30
A34: vale_pl_aj | B34: Vale — PL ajustado (Nota 8) | C34: 204083020 | E34: Nota 8 p.27
A35: vale_res_aj | B35: Vale — resultado ajustado (Nota 8) | C35: 13814281 | D35: 31592000 | E35: Nota 8 p.27; Nota 18 p.35 (2024 em R$ mi)
A36: p_dir | B36: Participação no capital social (Nota 8) | C36: 0.036 | D36: 0.036 | E36: Nota 8 p.27; Nota 18 p.35
A37: p_ex_tes | B37: Participação sem ações em tesouraria (V/T) | C37: 0.0383 | E37: Relatório da Administração — Estrutura dos Investimentos, p.3
A38: mercado | B38: Valor de mercado da participação na Vale | C38: 11754997 | D38: 8910993 | E38: Nota 8 (3) p.27
A39: div_dec_total | B39: Dividendos declarados 2025 pela Bradespar (DMPL) | C39: 680000 | D39: 450000 | E39: DMPL p.17
A40: jcp_dec_total | B40: JCP declarados 2025 pela Bradespar (DMPL) | C40: 567000 | D40: 422000 | E40: DMPL p.17
A41: rem_adm | B41: Remuneração do pessoal-chave (total) | C41: 18660 | D41: 15000 | E41: Nota 13 II p.32
A42: rem_limite | B42: Limite AGO 2025: remuneração + previdência | C42: 19910 | E42: Nota 13 II p.32 (19.391 + 519)
A43: desp_pessoal | B43: Despesas de pessoal | C43: 26755 | D43: 18463 | E43: Nota 16d p.34
A44: outras_dga | B44: Outras despesas gerais e administrativas | C44: 7786 | D44: 7823 | E44: Nota 16d p.34
A45: selic_proxy | B45: Taxa prefixada 1 ano usada no cenário-base da Nota 14 | C45: 0.138 | E45: Nota 14b p.33–34 (exemplo 13,80% a.a.)
A46: litel | B46: Contingência possível — Litel (R$ mil) | C46: 1400000 | E46: Nota 9 b-I p.27
A47: autuacao | B47: Contingência possível — autuação IRPJ/CSL (R$ mil) | C47: 979000 | E47: Nota 9 b-II p.28
A48: cred_trib | B48: Créditos tributários não ativados | C48: 355800 | D48: 345171 | E48: Nota 12c p.32

Sheet Materialidade
A1: PT 320 — Materialidade (R$ mil) — decisão didática; julgamento do preparador (matrícula 211014396)
A3: Referencial | B3: Base (R$ mil) | C3: % aplicado | D3: Resultado (R$ mil) | E3: Comentário
A4: Ativo total | B4: =Dados_DF!$C$4 -> 7999560 | C4: 0.01 | D4: =B4*C4 -> 79995.6 | E4: ESCOLHIDO para as DFs como um todo: ativo concentrado (92% em Investimentos) e usuários focados no valor da participação na Vale.
A5: Patrimônio líquido | B5: =Dados_DF!$C$14 -> 7647771 | C5: 0.01 | D5: =B5*C5 -> 76477.71 | E5: Alternativa convergente.
A6: Lucro antes do IR (resultado) | B6: =Dados_DF!$C$17 -> 546993 | C6: 0.05 | D6: =B6*C6 -> 27349.65 | E6: Volátil (−54% a/a) e derivado da investida: usado para MATERIALIDADE ESPECÍFICA de contas de resultado.
A7: Equivalência patrimonial (proxy de receita) | B7: =Dados_DF!$C$18 -> 571264 | C7: 0.05 | D7: =B7*C7 -> 28563.2 | E7: Referencial alternativo de resultado.
A9: Materialidade global adotada (arredondada) | D9: =ROUND(D4,-3) -> 80000
A10: Percentual para execução | C10: 0.7
A11: Materialidade para execução (PM) | D11: =D9*C10 -> 56000
A12: Limite de claramente trivial | C12: 0.05 | D12: =D9*C12 -> 4000
A13: Materialidade específica — contas de resultado e distribuições (5% do lucro) | D13: =ROUND(D6,-1) -> 27350
A14: PM específica (70%) | D14: =D13*C10 -> 19145
A15: Materialidade específica — remuneração de administradores / partes relacionadas | C15: 0.05 | D15: =ROUND(Dados_DF!$C$41*C15,0) -> 933 | E15: Sensibilidade qualitativa (NBC TA 320.A..; 550): 5% do total pago ao pessoal-chave.
A17: Teste de razoabilidade
A18: Materialidade global / lucro 2025 | D18: =D9/Dados_DF!$C$17 -> 0.14625416
A19: Materialidade global / PL | D19: =D9/Dados_DF!$C$14 -> 0.010460564
A20: Materialidade global / valor de mercado da Vale | D20: =D9/Dados_DF!$C$38 -> 0.0068056164
A21: Investimentos / ativo total | D21: =Dados_DF!$C$8/Dados_DF!$C$4 -> 0.918145

Sheet Concil_Investimento
A1: PT 500/510/330 — Roll-forward da conta Investimentos e conciliações com Notas 8, 10 e 13 (R$ mil)
A3: Item | B3: 2025 | C3: Fonte/observação
A4: Saldo inicial (31/12/2024) | B4: =Dados_DF!$D$8 -> 8153681 | C4: Balanço 2024 (comparativo)
A5: (+) Equivalência patrimonial | B5: =Dados_DF!$C$18 -> 571264 | C5: DRE; Nota 8
A6: (+/−) Reflexos em OCI | B6: =Dados_DF!$C$24 -> -135589 | C6: DRA/DMPL
A7: (−) JCP declarados pela Vale (bruto): recebidos + a receber | B7: =-(Dados_DF!$C$29+Dados_DF!$C$30) -> -566011 | C7: Nota 13 I
A8: (−) Dividendos declarados pela Vale: recebidos + a receber | B8: =-(Dados_DF!$C$31+Dados_DF!$C$32) -> -678589 | C8: Nota 13 I
A9: Total: saldo final calculado | B9: =SUM(B4:B8) -> 7344756
A10: Saldo final no Balanço | B10: =Dados_DF!$C$8 -> 7344756 | C10: Balanço
A11: Diferença (deve ser zero) | B11: =B9-B10 -> 0 | C11: Conciliação exata em R$ mil
A13: Conciliação de dividendos e JCP a receber (Balanço × Nota 13)
A14: JCP a receber bruto 2025 | B14: =Dados_DF!$C$30 -> 256391
A15: (−) IRRF 15% | B15: =-B14*Dados_DF!$C$33 -> -38458.65 | C15: Nota 10c: IRRF 15% sobre JCP
A16: (+) Dividendos a receber | B16: =Dados_DF!$C$32 -> 328708
A17: Total: dividendos e JCP a receber calculado | B17: =SUM(B14:B16) -> 546640.35
A18: Balanço (Dividendos e JCP a receber) | B18: =Dados_DF!$C$7 -> 546640
A19: Diferença (arredondamento) | B19: =B17-B18 -> 0.35 | C19: Aceitável: < R$ 1 mil
A20: 2024: JCP a receber bruto − IRRF | B20: =Dados_DF!$D$30*(1-Dados_DF!$D$33) -> 72276.35
A21: 2024: Balanço | B21: =Dados_DF!$D$7 -> 72276
A22: 2024: diferença | B22: =B20-B21 -> 0.35
A24: Conciliação do fluxo de caixa: JCP e dividendos recebidos (DFC) × Nota 13
A25: JCP recebidos 2025 (bruto) | B25: =Dados_DF!$C$29 -> 309620
A26: (−) IRRF 15% retido | B26: =-B25*Dados_DF!$C$33 -> -46443
A27: (+) Dividendos recebidos 2025 | B27: =Dados_DF!$C$31 -> 349881
A28: (+) Recebimento em 2025 do saldo a receber de 2024 | B28: =Dados_DF!$D$7 -> 72276
A29: Total: recebimentos calculados | B29: =SUM(B25:B28) -> 685334
A30: DFC — JCP e dividendos recebidos | B30: =Dados_DF!$C$27 -> 685334
A31: Diferença (deve ser ~0) | B31: =B29-B30 -> 0
A33: Verificação do valor patrimonial × participação
A34: Participação (Nota 8) × PL ajustado da Vale | B34: =Dados_DF!$C$36*Dados_DF!$C$34 -> 7346988.7
A35: Saldo contábil | B35: =Dados_DF!$C$8 -> 7344756
A36: Diferença | B36: =B35-B34 -> -2232.72
A37: Diferença / saldo | B37: =B36/B35 -> -0.00030398831
A38: Valor de mercado da participação | B38: =Dados_DF!$C$38 -> 11754997
A39: Mercado / contábil (indício de impairment? <1 = sim) | B39: =B38/B35 -> 1.6004612

Sheet Analiticos
A1: PT 520 — Procedimentos analíticos substantivos (R$ mil) — Realizado com evidência pública
A2: Limite de diferença aceitável sem investigação (NBC TA 520.5(d)) = PM específica de resultado (Materialidade!D14)
A4: Análise | B4: Expectativa | C4: Registrado | D4: Diferença | E4: Dif./registrado | F4: Limite aceitável | G4: Investigar? | H4: Comentário
A5: A1 Equivalência: 3,60% × resultado ajustado da Vale | B5: =Dados_DF!$C$36*Dados_DF!$C$35 -> 497314.12 | C5: =Dados_DF!$C$18 -> 571264 | D5: =C5-B5 -> 73949.884 | E5: =IF(C5=0,0,D5/C5) -> 0.12944958 | F5: =Materialidade!$D$14 -> 19145 | G5: =IF(ABS(D5)>F5,"SIM","não") -> SIM | H5: Participação direta sobre capital total (inclui ações em tesouraria da investida).
A6: A2 Equivalência: 3,83% (sem tesouraria) × resultado ajustado | B6: =Dados_DF!$C$37*Dados_DF!$C$35 -> 529086.96 | C6: =Dados_DF!$C$18 -> 571264 | D6: =C6-B6 -> 42177.038 | E6: =IF(C6=0,0,D6/C6) -> 0.073831079 | F6: =Materialidade!$D$14 -> 19145 | G6: =IF(ABS(D6)>F6,"SIM","não") -> SIM | H6: Expectativa mais precisa; resíduo ainda acima do limite: a % média ponderada ao longo de 2025 pode ser maior (recompras) — requer ITRs da Vale.
A7: A3 Investimento: 3,60% × PL ajustado da Vale | B7: =Dados_DF!$C$36*Dados_DF!$C$34 -> 7346988.7 | C7: =Dados_DF!$C$8 -> 7344756 | D7: =C7-B7 -> -2232.72 | E7: =IF(C7=0,0,D7/C7) -> -0.00030398831 | F7: =Materialidade!$D$14 -> 19145 | G7: =IF(ABS(D7)>F7,"SIM","não") -> não | H7: Alta aderência (0,03%).
A8: A4 Receita de aplicações: taxa 13,80% × média simples do caixa | B8: =Dados_DF!$C$45*AVERAGE(Dados_DF!$C$6,Dados_DF!$D$6) -> 21138.288 | C8: =Dados_DF!$C$22 -> 55506 | D8: =C8-B8 -> 34367.712 | E8: =IF(C8=0,0,D8/C8) -> 0.61917112 | F8: =Materialidade!$D$14 -> 19145 | G8: =IF(ABS(D8)>F8,"SIM","não") -> SIM | H8: Média simples não reflete saldos intra-anuais (JCP/dividendos recebidos de R$ 685 mi e pagamentos de R$ 940 mi). Precisão insuficiente.
A9: A5 Despesas G&A: pessoal 2025 + outras despesas de 2024 | B9: =Dados_DF!$C$43+Dados_DF!$D$44 -> 34578 | C9: =-Dados_DF!$C$19 -> 34541 | D9: =C9-B9 -> -37 | E9: =IF(C9=0,0,D9/C9) -> -0.0010711908 | F9: =Materialidade!$D$14 -> 19145 | G9: =IF(ABS(D9)>F9,"SIM","não") -> não | H9: Aumento de G&A explicado pelo aumento de pessoal (R$ 18.463 → 26.755 mil).
A10: A6 Remuneração do pessoal-chave vs limite aprovado em AGO | B10: =Dados_DF!$C$42 -> 19910 | C10: =Dados_DF!$C$41 -> 18660 | D10: =C10-B10 -> -1250 | E10: =IF(C10=0,0,D10/C10) -> -0.06698821 | F10: =Materialidade!$D$14 -> 19145 | G10: =IF(ABS(D10)>F10,"SIM","não") -> não | H10: Dentro do limite (R$ 19.391 + R$ 519).
A11: A7 DFC: variação de caixa = op. + invest. + financ. | B11: =Dados_DF!$C$25+Dados_DF!$C$26 -> -269548 | C11: =Dados_DF!$C$28 -> -269548 | D11: =C11-B11 -> 0 | E11: =IF(C11=0,0,D11/C11) -> 0 | F11: =Materialidade!$D$14 -> 19145 | G11: =IF(ABS(D11)>F11,"SIM","não") -> não | H11: Fecha com 0 de investimentos em 2025.
A12: A8 Caixa final = inicial + variação | B12: =Dados_DF!$D$6+Dados_DF!$C$28 -> 18402 | C12: =Dados_DF!$C$6 -> 18402 | D12: =C12-B12 -> 0 | E12: =IF(C12=0,0,D12/C12) -> 0 | F12: =Materialidade!$D$14 -> 19145 | G12: =IF(ABS(D12)>F12,"SIM","não") -> não | H12: Fecha exatamente.
A13: A9 Dividendos+JCP declarados (DMPL) × declarados Bradespar (Nota 10c) | B13: =1247000 -> 1247000 | C13: =Dados_DF!$C$39+Dados_DF!$C$40 -> 1247000 | D13: =C13-B13 -> 0 | E13: =IF(C13=0,0,D13/C13) -> 0 | F13: =Materialidade!$D$14 -> 19145 | G13: =IF(ABS(D13)>F13,"SIM","não") -> não | H13: Nota 10c total 2025 R$ 1.247.000 mil vs DMPL R$ 1.247.000 mil.

Sheet Liquidez_Continuidade
A1: PT 570 — Continuidade operacional / liquidez (R$ mil) — Realizado com evidência pública (limitado às DFs)
A3: Indicador | B3: 2025 | C3: 2024 | D3: Comentário
A4: Liquidez corrente (AC/PC) | B4: =Dados_DF!$C$5/Dados_DF!$C$12 -> 1.6247668 | C4: =Dados_DF!$D$5/Dados_DF!$D$12 -> 2.9701347 | D4: Reduziu em 2025, mas permanece > 1
A5: Caixa / passivo circulante | B5: =Dados_DF!$C$6/Dados_DF!$C$12 -> 0.052906524 | C5: =Dados_DF!$D$6/Dados_DF!$D$12 -> 2.3716766 | D5: Cobertura por caixa caiu: depende de recebimentos da Vale
A6: (Caixa + Div/JCP a receber) / Div/JCP a pagar | B6: =(Dados_DF!$C$6+Dados_DF!$C$7)/Dados_DF!$C$15 -> 1.7849275 | C6: =(Dados_DF!$D$6+Dados_DF!$D$7)/Dados_DF!$D$15 -> 4.0964565 | D6: Obrigação com acionistas coberta por recebíveis da Vale
A7: Dívida financeira | B7: 0 | C7: 0 | D7: Sem empréstimos/financiamentos nas DFs (Notas 14 e 16)
A8: Caixa operacional / distribuições pagas | B8: =Dados_DF!$C$25/-Dados_DF!$C$26 -> 0.71311344 | C8: =Dados_DF!$D$25/-Dados_DF!$D$26 -> 1.057341 | D8: <1: distribuições superiores ao caixa gerado; consumo do caixa acumulado
A9: Passivos contingentes possíveis (Litel + autuação) | B9: =Dados_DF!$C$46+Dados_DF!$C$47 -> 2379000 | D9: Não provisionados (Nota 9)
A10: … como % do PL | B10: =B9/Dados_DF!$C$14 -> 0.31107103
A11: … como % do valor de mercado da Vale | B11: =B9/Dados_DF!$C$38 -> 0.20238202 | D11: Capacidade de pagamento via venda de ações, em tese
A12: … vezes o caixa e equivalentes | B12: =B9/Dados_DF!$C$6 -> 129.27943 | D12: Sem liquidez imediata — gatilho de atenção se houver perda provável
A13: Créditos tributários não ativados | B13: =Dados_DF!$C$48 -> 355800 | C13: =Dados_DF!$D$48 -> 345171 | D13: Não reconhecidos; sem impacto no balanço

Sheet Parametros_MUS
A1: PT 530 — Parâmetros da amostragem por unidade monetária (R$) — BASE SINTÉTICA — Simulado para fins didáticos
A3: Valor contábil da população (R$) | B3: 7.3722732e+09
A4: Distorção tolerável = PM (R$) | B4: =Materialidade!D11*1000 -> 56000000
A5: Distorção esperada (R$) — hipótese | B5: 5000000
A6: Fator de confiança (zero erros, 95%) | B6: 2.9957
A7: Fator de expansão (95%) | B7: 1.6
A8: Tamanho da amostra = VC × FC / (TM − DE × FE) | B8: =ROUNDUP(B3*B6/(B4-B5*B7),0) -> 461
A9: Intervalo de amostragem (R$) | B9: =B3/B8 -> 15991916
A11: Resultados da execução (script 03_amostragem_mus.py)
A12: Valor contábil da população (R$) | B12: 7.3722732e+09
A13: Materialidade global (R$) | B13: 80000000
A14: Materialidade para execução = distorção tolerável (R$) | B14: 56000000
A15: Distorção esperada assumida (R$) | B15: 5000000
A16: Fator de confiança (zero erros), 95% | B16: 2.9957
A17: Fator de expansão | B17: 1.6
A18: Tamanho calculado da amostra | B18: 461
A19: Intervalo de amostragem (R$) | B19: 15991916
A20: Itens do estrato topo (>= intervalo) | B20: 0
A21: Itens selecionados no estrato sistemático | B21: 461
A22: Itens na amostra (total) | B22: 461
A23: Início aleatório (R$) | B23: 9799321.6
... A29: UEL / distorção tolerável | B29: 1.305
A30: Conclusão da amostra | B30: UEL > TM: amostra NÃO apoia aceitação sem ajustes/ampliação

Sheet Mapa_Distorcoes
A1: PT 450 — Mapa de distorções (BASE SINTÉTICA) — valores em R$ — Simulado para fins didáticos
A3: tipo_erro | B3: inseridos | C3: natureza | D3: efeito_inserido_brl | E3: detectados_populacao | F3: selecionados_amostra | G3: detectados_amostra | H3: recall_populacao_%
A4: E1a | B4: 400 | C4: valor | D4: 120487.18 | E4: 400 | F4: 0 | G4: 0 | H4: 100
A5: E1b | B5: 300 | C5: valor | D5: -9685.25 | E5: 300 | F5: 0 | G5: 0 | H5: 100
A6: E2 | B6: 350 | C6: valor | D6: 13918505 | E6: 350 | F6: 1 | G6: 1 | H6: 100
A7: E3 | B7: 300 | C7: valor | D7: 4759984.3 | E7: 300 | F7: 0 | G7: 0 | H7: 100
A8: E4 | B8: 150 | C8: corte | D8: 172027.94 | E8: 150 | F8: 0 | G8: 0 | H8: 100
A9: E5 | B9: 200 | C9: valor | D9: 8365652.2 | E9: 200 | F9: 0 | G9: 0 | H9: 100
A10: E6 | B10: 60 | C10: integridade | D10: 0 | E10: 60 | F10: 0 | G10: 0 | H10: 100
A11: E7 | B11: 40 | C11: valor | D11: -345037.87 | E11: 40 | F11: 0 | G11: 0 | H11: 100
A12: E8 | B12: 80 | C12: classificacao | D12: -832874.79 | E12: 80 | F12: 0 | G12: 0 | H12: 100
A13: E9 | B13: 150 | C13: valor | D13: 661749.88 | E13: 0 | F13: 0 | G13: 0 | H13: 0
A14: TOTAL | B14: 2030 | D14: 26810809 | E14: 1880 | F14: 1 | G14: 1 | H14: 92.6
A16: Materialidade global (R$) | D16: =Materialidade!D9*1000 -> 80000000
A17: Materialidade para execução (R$) | D17: =Materialidade!D11*1000 -> 56000000
A18: Limite de trivial (R$) | D18: =Materialidade!D12*1000 -> 4000000
A19: Efeito líquido (natureza 'valor') / materialidade global | D19: =D20/D16 -> 0.34339569
A20: Efeito líquido inserido (natureza valor) — R$ | D20: 27471656
A21: Efeito líquido / materialidade para execução | D21: =D20/D17 -> 0.49056528
A22: Parcela que afeta resultado (E1a + E5) — R$ | D22: 8486139.4
A23: Parcela de resultado / materialidade específica de resultado | D23: =D22/(Materialidade!D13*1000) -> 0.31027932

Sheet Conc_Razao_Balanco
A1: PT 500 — Conciliação do razão auxiliar sintético com o Balanço (R$) — Simulado para fins didáticos
A3: Item | B3: Valor (R$)
A4: Saldo contábil — Balanço 31/12/2025 (Investimentos) | B4: 7344756000
A5: (+) Duplicidades (T3) | B5: 4759984.3
A6: (+/−) Quantidade registrada diverge da custódia (T2) | B6: 13918505
A7: (+/−) Valores sem aderência ao pro rata/soma (T1, T5, T8) | B7: 8131091.3
A8: (+) Excesso de ações no total de controle (T0): 14,718 ações × R$ 44.9619 — NÃO localizado por linha | B8: 661749.68
A9: Total: saldo esperado do razão auxiliar (todas as contas) | B9: 7.3722273e+09
A10: Soma observada do razão auxiliar (todas as contas) | B10: 7.3722277e+09
A11: Diferença residual não explicada (arredondamento/precisão) | B11: 325.46
A12: (−) Registros em conta indevida (T9) | B12: -832874.79
A13: Total: soma do razão auxiliar na conta 1.2.1.01 | B13: 7.3713948e+09
A14: Diferença total da conta 1.2.1.01 vs. Balanço | B14: 26638781

Sheet Testes_Populacao
A1: PT 240/520/530 — Resultado dos testes em 100% da base sintética — Simulado para fins didáticos
A3: teste | B3: registros_alertados | C3: soma_saldo_alertado_brl | D3: efeito_estimado_brl
A4: T1_soma | B4: 300 | C4: 4179957.2 | D4: -9685.47
A5: T2_qtd_vs_custodia | B5: 410 | C5: 20587933 | D5: 13918505
A6: T3_duplicidade_lote | B6: 300 | C6: 4759984.3 | D6: 4759984.3
A7: T4_qtd_invalida | B7: 60 | C7: 809224.81 | D7: -0.05
A8: T5_prorata_recalculo | B8: 640 | C8: 16753739 | D8: 8141101.1
A9: T6_corte_pos_emissao | B9: 150 | C9: 2211767.3 | D9: -0.1
A10: T7a_manual_fim_semana | B10: 201 | C10: 11009639 | D10: 8365652.1
A11: T7b_manual_madrugada | B11: 200 | C11: 10992958 | D11: 8365652.1
A12: T7c_usuario_nao_autorizado | B12: 109 | C12: 6315105.5 | D12: 4704748.9
A13: T7d_valor_redondo | B13: 200 | C13: 10992958 | D13: 8365652.1
A14: T8_saldo_zero_com_qtd | B14: 40 | C14: 0 | D14: -345037.88
A15: T9_conta_indevida | B15: 80 | C15: 832874.79 | D15: -0.04
A16: T0_total_controle_acoes | B16: 0 | C16: 0 | D16: 661749.68
